autokit/ExecutableType.py
autokit/ExternalTool.py
autokit/PlatformData.py
autokit/ToolConfig.py
autokit/__init__.py
autokit/downloader.py
autokit/progressBar.py
autokit-0.14.16.dist-info/LICENSE
autokit-0.14.16.dist-info/METADATA
autokit-0.14.16.dist-info/WHEEL
autokit-0.14.16.dist-info/top_level.txt
autokit-0.14.16.dist-info/RECORD
