Metadata-Version: 2.1
Name: autokit
Version: 0.14.16
Summary: A simple tool to automate the installation and integration of external tools.
Home-page: https://github.com/lukasgolson/Autokit
Author: Lukas G. Olson
Author-email: olson@student.ubc.ca
License: LICENSE
Classifier: License :: OSI Approved :: MIT License
Classifier: Programming Language :: Python
Classifier: Programming Language :: Python :: 3
Classifier: Development Status :: 4 - Beta
License-File: LICENSE
Provides-Extra: tqdm
Requires-Dist: tqdm ; extra == 'tqdm'
